PyNSP-0.2.1.data/scripts/pynsp
pynsp/__init__.py
pynsp/base.py
pynsp/bin/__init__.py
pynsp/core/__init__.py
pynsp/core/base.py
pynsp/core/handler.py
pynsp/core/io.py
pynsp/core/ui.py
pynsp/cython/__init__.py
pynsp/cython/test.py
pynsp/methods/__init__.py
pynsp/methods/qc.py
pynsp/methods/rsfc.py
pynsp/methods/signal.py
pynsp/methods/stats.py
pynsp/methods/tools.py
pynsp/networks/__init__.py
pynsp/stats/__init__.py
pynsp/stats/correlation.py
pynsp/stats/normalization.py
pynsp/tools/__init__.py
pynsp/tools/checker.py
pynsp/tools/io.py
pynsp/tools/parallel.py
pynsp/tools/roi.py
pynsp/tools/signal.py
PyNSP-0.2.1.dist-info/LICENSE
PyNSP-0.2.1.dist-info/METADATA
PyNSP-0.2.1.dist-info/WHEEL
PyNSP-0.2.1.dist-info/top_level.txt
PyNSP-0.2.1.dist-info/RECORD
