Metadata-Version: 2.1
Name: PyNSP
Version: 0.2.1
Summary: Python Neural-Signal Processing
Home-page: UNKNOWN
Author: SungHo Lee
Author-email: shlee@unc.edu
License: GNLv3
Keywords: Python Neural-Signal Processing
Platform: UNKNOWN
Classifier: Development Status :: 3 - Alpha
Classifier: Framework :: Jupyter
Classifier: Intended Audience :: Science/Research
Classifier: Topic :: Scientific/Engineering :: Information Analysis
Classifier: Natural Language :: English
Classifier: Programming Language :: Python :: 2.7
